{
  "@context": "http://iiif.io/api/image/2/context.json",
  "@id": "https://DanielaTGomes.github.io/imagens_omeka/resultado//ML_ESC_0752",
  "height": 4633,
  "profile": [
    "http://iiif.io/api/image/2/level0.json",
    {
      "formats": [
        "jpg"
      ],
      "qualities": [
        "default"
      ]
    }
  ],
  "protocol": "http://iiif.io/api/image",
  "sizes": [
    {
      "height": 290,
      "width": 315
    },
    {
      "height": 145,
      "width": 157
    },
    {
      "height": 72,
      "width": 79
    },
    {
      "height": 36,
      "width": 39
    },
    {
      "height": 18,
      "width": 20
    },
    {
      "height": 9,
      "width": 10
    },
    {
      "height": 5,
      "width": 5
    },
    {
      "height": 2,
      "width": 2
    },
    {
      "height": 1,
      "width": 1
    },
    {
      "height": 1,
      "width": 1
    }
  ],
  "tiles": [
    {
      "height": 512,
      "scaleFactors": [
        1,
        2,
        4,
        8
      ],
      "width": 512
    }
  ],
  "width": 5037
}